retui/__init__.py
retui/base.py
retui/helper.py
retui/mapping.py
retui/theme.py
retui/widget.py
retui/input_handling/__init__.py
retui/logger/__init__.py
retui-0.0.1.dist-info/LICENSE
retui-0.0.1.dist-info/METADATA
retui-0.0.1.dist-info/WHEEL
retui-0.0.1.dist-info/top_level.txt
retui-0.0.1.dist-info/RECORD
