Metadata-Version: 2.1
Name: retui
Version: 0.0.1
Summary: retui - simple TUI framework
Author-email: Bartlomiej Cieszkowski <bartlomiej.cieszkowski@gmail.com>
License: MIT License
Project-URL: Homepage, https://github.com/bartlomiejcieszkowski/retui
Project-URL: Bug Tracker, https://github.com/bartlomiejcieszkowski/retui/issues
Keywords: tui,console,framework
Classifier: License :: OSI Approved :: MIT License
Classifier: Programming Language :: Python :: 3
Requires-Python: >=3.6
License-File: LICENSE
